{"version":1,"resource":"vscode-userdata:/c%3A/Users/82108/AppData/Roaming/Code/User/settings.json","entries":[{"id":"XCMp.json","timestamp":1694428519403},{"id":"YlfH.json","timestamp":1694428686014},{"id":"XZzs.json","timestamp":1694428744504},{"id":"ryhS.json","timestamp":1694755090286},{"id":"5liR.json","timestamp":1694755156380},{"id":"gtEc.json","timestamp":1694755197246},{"id":"i78m.json","timestamp":1694755322216},{"id":"GOYJ.json","timestamp":1694755652647},{"id":"ea28.json","timestamp":1694755775953},{"id":"0Cud.json","timestamp":1694756465682},{"id":"6lAT.json","timestamp":1694756680435},{"id":"7ms2.json","timestamp":1701426948908}]}